[
    {
        "title": "Test – I",
        "description": "for Autonomous 2nd, 4th, 6th and 8th Semester UG and 2nd and 4th Semester PG EVEN 2024",
        "timeAgo": "6-03-2024"
    },
    {
        "title": "Revised - End Semester Examination",
        "description": "Schedule_ODD 2023_PHASE - II",
        "timeAgo": "15-01-2024"
    },
    {
        "title": "End Semester",
        "description": "Examination Schedule_ODD 2023_PHASE - II",
        "timeAgo": "15-01-2024"
    },
    {
        "title": "Examination",
        "description": "Schedule_ODD 2023_TEST II",
        "timeAgo": "10-01-2024"
    },
    {
        "title": "NOTICE",
        "description": "Test - II for Autonomous 1st Semester UG and PG and 3rd Semester (LATERAL only) ODD 2023",
        "timeAgo": "15-01-2024"
    },
    {
        "title": "SEE for",
        "description": "Autonomous 1st Semester UG and PG and 3rd Semester (LATERAL only) ODD 2023",
        "timeAgo": "10-01-2024"
    },
    {
        "title": "NOTICE_TUITION",
        "description": "HOSTEL FEES",
        "timeAgo": "16-12-2023"
    },
    {
        "title": "Test - I_Examination",
        "description": "Schedule_ODD 2023_SEM 1",
        "timeAgo": "13-12-2023"
    },
    {
        "title": "Test - I for",
        "description": "Autonomous 1st Semester UG and PG ODD 2023",
        "timeAgo": "13-12-2023"
    },
    {
        "title": "Modified_SEE",
        "description": "Examination Schedule_ODD 2023",
        "timeAgo": "09-12-2023"
    },
    {
        "title": "SEE Examination",
        "description": "Schedule_ODD 2023",
        "timeAgo": "01-12-2023"
    },
    {
        "title": "Examination",
        "description": "Schedule_ODD 2023_TEST II (Autonomous)",
        "timeAgo": "22-11-2023"
    },
    {
        "title": "SEE for",
        "description": "Autonomous UG 3rd, 5th and 7th Semester and PG 3rd Semester ODD 2023 (AY 2023–24)",
        "timeAgo": "11-11-2023"
    },
    {
        "title": "Autonomous-Class",
        "description": "Test - I_Examination Schedule_ODD 2023",
        "timeAgo": "03-10-2023"
    },
    {
        "title": "NOTICE_Test-",
        "description": "Autonomous 3rd, 5th and 7th Semester UG and 3rd Semester PG ODD 2023",
        "timeAgo": "03-10-2023"
    },
    {
        "title": "NOTICE - NON",
        "description": "AICTE ODD SEM 2023 CA3",
        "timeAgo": "29-09-2023"
    },
    {
        "title": "Separate",
        "description": "Supplementary Examination Schedule 2023",
        "timeAgo": "09-08-2023"
    },
    {
        "title": "Separate",
        "description": "Supplementary Examination Form Fill-up under Autonomous",
        "timeAgo": "04-08-2023"
    },
    {
        "title": "NOTICE - Odd",
        "description": "Semester Fees payment (Diploma)",
        "timeAgo": "03-08-2023"
    },
    {
        "title": "NOTICE - PPR",
        "description": "for EVEN Semester Examinations 2022-23",
        "timeAgo": "28-07-2023"
    },
    {
        "title": "NOTICE - Result",
        "description": "Publication of UG 2nd, 4th and 6th semester and PG 2nd semester EVEN 2022-23 REGULAR & BACKLOG",
        "timeAgo": "27-07-2023"
    },
    {
        "title": "Upload",
        "description": "Notice - EWYLS",
        "timeAgo": "03-07-2023"
    },
    {
        "title": "Result",
        "description": "Publication of B.Tech. 8th semester and PG 4th semester EVEN 2022-23 REGULAR & BACKLOG",
        "timeAgo": "03-07-2023"
    },
    {
        "title": "Notice for",
        "description": "Fees Payment (Odd Semester 2023-24)",
        "timeAgo": "12-06-2023"
    },
    {
        "title": "Revised Even",
        "description": "Semester Exam Routine of 2nd Sem UG and PG-Regular",
        "timeAgo": "08-06-2023"
    },
    {
        "title": "Revised Even",
        "description": "Semester Exam Routine of 4th Sem UG and PG-Regular",
        "timeAgo": "08-06-2023"
    },
    {
        "title": "Revised Even",
        "description": "Semester Exam Routine of 6th Sem UG and PG-Regular",
        "timeAgo": "08-06-2023"
    },
    {
        "title": "Even Semester",
        "description": "Exam Routine of 2nd Sem 2023. - Backlog",
        "timeAgo": "07-06-2023"
    },
    {
        "title": "Updated Even",
        "description": "Semester Exam Routine of 6th Sem UG and PG-Regular",
        "timeAgo": "07-06-2023"
    },
    {
        "title": "Even Semester",
        "description": "Exam Routine of 4th Sem 2023. - Backlog",
        "timeAgo": "07-06-2023"
    },
    {
        "title": "Even Semester",
        "description": "Exam Routine of 6th Sem 2023. - Backlog",
        "timeAgo": "07-06-2023"
    },
    {
        "title": "Updated Even",
        "description": "Semester Exam Routine of 2nd Sem UG and PG-Regular",
        "timeAgo": "07-06-2023"
    },
    {
        "title": "Updated Even",
        "description": "Semester Exam Routine of 4th Sem UG and PG-Regular",
        "timeAgo": "07-06-2023"
    },
    {
        "title": "Examination",
        "description": "Schedule full - BACKLOG-CE801A",
        "timeAgo": "19-05-2023"
    },
    {
        "title": "Exam schedule",
        "description": "of 2nd sem UG and PG",
        "timeAgo": "18-05-2023"
    },
    {
        "title": "Exam schedule",
        "description": "of 4th sem UG",
        "timeAgo": "18-05-2023"
    },
    {
        "title": "Exam schedule",
        "description": "of 6th sem UG",
        "timeAgo": "18-05-2023"
    },
    {
        "title": "Examination",
        "description": "Schedule full - BACKLOG-CE801A",
        "timeAgo": "19-05-2023"
    },
    {
        "title": "Exam schedule",
        "description": "of 2nd sem UG and PG",
        "timeAgo": "18-05-2023"
    },
    {
        "title": "Exam schedule",
        "description": "of 4th sem UG",
        "timeAgo": "18-05-2023"
    },
    {
        "title": "Exam schedule",
        "description": "of 6th sem UG",
        "timeAgo": "18-05-2023"
    },
    {
        "title": "TEST-2",
        "description": "of 2nd-SEM UG and PG",
        "timeAgo": "12-05-2023"
    },
    {
        "title": "TEST-2 of",
        "description": "4th SEM UG",
        "timeAgo": "12-05-2023"
    },
    {
        "title": "TEST-2-OF-6TH-SEM.pdf",
        "description": "",
        "timeAgo": "12-05-2023"
    },
    {
        "title": "NOTICE Test - II",
        "description": "for Autonomous 2nd, 4th and 6th Semester UG and 2nd Semester PG EVEN 2023",
        "timeAgo": "10-05-2023"
    },
    {
        "title": "Even Semester",
        "description": "Examination Schedule_PG-4th Sem-MBA-MCA",
        "timeAgo": "28-04-2023"
    },
    {
        "title": "Even Semester",
        "description": "Examination Schedule - 8th Sem",
        "timeAgo": "28-04-2023"
    },
    {
        "title": "Examination",
        "description": "Schedule - TEST-I-EVEN-2ND-SEM",
        "timeAgo": "19-04-2023"
    },
    {
        "title": "Examination",
        "description": "Schedule - TEST-II-EVEN-8TH-SEM",
        "timeAgo": "19-04-2023"
    },
    {
        "title": "EVEN End",
        "description": "Semester Examination 2023 Form Fill Up under Autonomous Status",
        "timeAgo": "17-04-2023"
    },
    {
        "title": "NOTICE_Test - I",
        "description": "for Autonomous 1st Semester both UG and PG and Test – II for Autonomous 8th Semester UG and 4th Semester PG EVEN 2023",
        "timeAgo": "11-04-2023"
    },
    {
        "title": "NOTICE - PPR",
        "description": "for ODD Semester Examinations 2022-23 (1st semester only)",
        "timeAgo": "06-04-2023"
    },
    {
        "title": "NOTICE_Test - I",
        "description": "for Autonomous 4th, 6th an 8th Semester EVEN 2023",
        "timeAgo": "17-03-2023"
    },
    {
        "title": "Examination",
        "description": "Schedule_TEST - I_4_6_8 SEM_EVEN 2022",
        "timeAgo": "17-03-2023"
    },
    {
        "title": "Notice",
        "description": "Non AICTE Class Test Even Sem 2023",
        "timeAgo": "17-03-2023"
    },
    {
        "title": "NOTICE - PPR",
        "description": "for EVEN Semester Examinations 2022-23 and PPR Application Form",
        "timeAgo": "21-02-2023"
    },
    {
        "title": "Notice for",
        "description": "Fees Payment (Even Semester 2022-23)",
        "timeAgo": "10-02-2023"
    },
    {
        "title": "Semester End",
        "description": "Examination schedule for 1st semester UG and PG",
        "timeAgo": "24-01-2023"
    },
    {
        "title": "NOTICE for",
        "description": "SEE & CLASS TEST-II 1ST SEMESTER",
        "timeAgo": "09-01-2023"
    }
]
